gerapy_playwright/__init__.py
gerapy_playwright/__version__.py
gerapy_playwright/downloadermiddlewares.py
gerapy_playwright/pretend.py
gerapy_playwright/request.py
gerapy_playwright/settings.py
gerapy_playwright/utils.py
gerapy_playwright-0.2.4.dist-info/METADATA
gerapy_playwright-0.2.4.dist-info/WHEEL
gerapy_playwright-0.2.4.dist-info/top_level.txt
gerapy_playwright-0.2.4.dist-info/RECORD
